setup.py
examples/example_local.py
examples/example_with_download.py
llm4bi_embedders/__init__.py
llm4bi_embedders/docembedder.py
llm4bi_embedders/train.py
llm4bi_embedders/src/__init__.py
llm4bi_embedders/src/dataset.py
llm4bi_embedders/src/lightningMods.py
llm4bi_embedders/src/loss.py
llm4bi_embedders/src/model.py
llm4bi_embedders/src/utils/__init__.py
llm4bi_embedders/src/utils/general.py
llm4bi_embedder-0.2.3.dist-info/METADATA
llm4bi_embedder-0.2.3.dist-info/WHEEL
llm4bi_embedder-0.2.3.dist-info/licenses/LICENSE
llm4bi_embedder-0.2.3.dist-info/RECORD
