Metadata-Version: 2.1
Name: llm4bi_embedder
Version: 0.2.3
Summary: Package including any embedder for the LLM4BI project
Author-email: Luis Garcia <admin@huginns.io>
License-File: LICENSE
Classifier: License :: OSI Approved :: GNU General Public License v3 (GPLv3)
Classifier: Operating System :: OS Independent
Classifier: Programming Language :: Python :: 3
Requires-Python: >=3.7
Requires-Dist: fastparquet
Requires-Dist: google-cloud-storage
Requires-Dist: lightning
Requires-Dist: pandas
Requires-Dist: pyarrow
Requires-Dist: transformers
Requires-Dist: wandb
